rookiepy-0.5.5.dist-info/METADATA
rookiepy-0.5.5.dist-info/WHEEL
rookiepy/rookiepy.pyi
rookiepy/__init__.py
rookiepy/py.typed
rookiepy/rookiepy.pypy38-pp73-ppc_64-linux-gnu.so
rookiepy-0.5.5.dist-info/RECORD
